k8s_deployment_status/__init__.py
k8s_deployment_status/config.py
k8s_deployment_status/main.py
k8s_deployment_status-0.0.6.dist-info/LICENSE
k8s_deployment_status-0.0.6.dist-info/METADATA
k8s_deployment_status-0.0.6.dist-info/WHEEL
k8s_deployment_status-0.0.6.dist-info/top_level.txt
k8s_deployment_status-0.0.6.dist-info/RECORD
