Metadata-Version: 2.1
Name: k8s-deployment-status
Version: 0.0.6
Summary: Provides deployment status details for any Kubernetes pod
Author-email: saltgen <sdnirvana94@gmail.com>
Project-URL: homepage, https://github.com/saltgen/k8s_deployment_status
Project-URL: repository, https://github.com/saltgen/k8s_deployment_status
Project-URL: issues, https://github.com/saltgen/k8s_deployment_status/issues
Keywords: openshift,ecs,kubernetes,deployment,status,devops,k8s,pod,container
Classifier: Programming Language :: Python :: 3
Classifier: License :: OSI Approved :: MIT License
Classifier: Operating System :: OS Independent
Requires-Python: >=3.6
License-File: LICENSE
Requires-Dist: kubernetes (>=26.1.0)
Requires-Dist: requests (>=2.25.1)
